CHANGES.md
LICENSE
MANIFEST.in
README.md
setup.py
OpenKVK/Client.py
OpenKVK/__init__.py
OpenKVK/cli.py
OpenKVK.egg-info/PKG-INFO
OpenKVK.egg-info/SOURCES.txt
OpenKVK.egg-info/dependency_links.txt
OpenKVK.egg-info/entry_points.txt
OpenKVK.egg-info/requires.txt
OpenKVK.egg-info/top_level.txt
OpenKVK/examples/apiclient.py
OpenKVK/examples/baseclient.py
OpenKVK/examples/querybuilder.py
OpenKVK/test/__init__.py
OpenKVK/test/test_openkvk.py
docs/Makefile
docs/OpenKVK.rst
docs/OpenKVK.test.rst
docs/conf.py
docs/index.rst
docs/make.bat
docs/_build/doctrees/OpenKVK.doctree
docs/_build/doctrees/OpenKVK.test.doctree
docs/_build/doctrees/environment.pickle
docs/_build/doctrees/index.doctree
docs/_build/html/.buildinfo
docs/_build/html/OpenKVK.html
docs/_build/html/OpenKVK.test.html
docs/_build/html/genindex.html
docs/_build/html/index.html
docs/_build/html/objects.inv
docs/_build/html/py-modindex.html
docs/_build/html/search.html
docs/_build/html/searchindex.js
docs/_build/html/_modules/index.html
docs/_build/html/_modules/OpenKVK/Client.html
docs/_build/html/_modules/OpenKVK/cli.html
docs/_build/html/_modules/OpenKVK/test/test_openkvk.html
docs/_build/html/_sources/OpenKVK.test.txt
docs/_build/html/_sources/OpenKVK.txt
docs/_build/html/_sources/index.txt
docs/_build/html/_static/ajax-loader.gif
docs/_build/html/_static/basic.css
docs/_build/html/_static/comment-bright.png
docs/_build/html/_static/comment-close.png
docs/_build/html/_static/comment.png
docs/_build/html/_static/darkmetal.png
docs/_build/html/_static/default.css
docs/_build/html/_static/doctools.js
docs/_build/html/_static/down-pressed.png
docs/_build/html/_static/down.png
docs/_build/html/_static/file.png
docs/_build/html/_static/headerbg.png
docs/_build/html/_static/jquery.js
docs/_build/html/_static/logo.png
docs/_build/html/_static/metal.png
docs/_build/html/_static/minus.png
docs/_build/html/_static/nature.css
docs/_build/html/_static/navigation.png
docs/_build/html/_static/plus.png
docs/_build/html/_static/print.css
docs/_build/html/_static/pygments.css
docs/_build/html/_static/scrolls.css
docs/_build/html/_static/searchtools.js
docs/_build/html/_static/sidebar.js
