Metadata-Version: 1.1
Name: OpenKVK
Version: 0.3
Summary: Python API wrapper for the OpenKVK service
Home-page: http://github.com/jeff-99/OpenKVK
Author: Jeff Slort
Author-email: j_slort@hotmail.com
License: MIT
Platform: any
Classifier: Programming Language :: Python
Classifier: Development Status :: 4 - Beta
Classifier: Natural Language :: English
Classifier: Environment :: Web Environment
Classifier: Intended Audience :: Developers
Classifier: License :: OSI Approved :: MIT License
Classifier: Operating System :: OS Independent
Classifier: Topic :: Software Development :: Libraries :: Python Modules
Classifier: Topic :: Internet :: WWW/HTTP :: Dynamic Content
Classifier: Topic :: Office/Business
